concatenate.v
module concatenation_operator();

  reg[3:0] r_VAL_1 = 4'b0111;
  reg[3:0] r_VAL_2 = 4'b1100;
  wire[7:0] w_CAT;

  reg[3:0] r_UNSIGNED = 4'b0010;
  reg signed [3:0] r_SIGNED = 4'b1110;
  wire[7:0] w_CAT_2;
  wire[15:0] w_CAT_3;

  reg r_CLOCK = 1'b0;
  reg [7:0] r_SHIFT_REG = 8'h01;

  // demonstrates a common concatenation
  assign w_CAT = {r_VAL_1, r_VAL_2};

  assign w_CAT_2 = {r_SIGNED, r_UNSIGNED};
  assign w_CAT_3 = {w_CAT, w_CAT_2};

  initial
    begin
      $dumpfile("concatenation.vcd");
      $dumpvars(0, concatenation_operator);
      #5;
      $display("Concatenation of %h and %h is %h", r_VAL_1, r_VAL_2, w_CAT);
      #20;
      $display("Concatenation of %h and %h is %h", r_SIGNED, r_UNSIGNED, w_CAT_2);
      #20;
      $display ("Concatenation of two 4-bit regs into a 16-bit reg: %h", w_CAT_3);
      #20;
      $display("Complete");
      $finish;   
    end

  // generate a clock
  always #1 r_CLOCK = ~r_CLOCK;

  // demonstrate shifting of a 1 through an 8 bit register
  always @ (posedge r_CLOCK)
  begin
    r_SHIFT_REG <= {r_SHIFT_REG[6:0], r_SHIFT_REG[7]};
  end

endmodule

concatenation.vcd
$date
	Wed Mar 25 17:01:34 2026
$end
$version
	Icarus Verilog
$end
$timescale
	1s
$end
$scope module concatenation_operator $end
$var wire 16 ! w_CAT_3 [15:0] $end
$var wire 8 " w_CAT_2 [7:0] $end
$var wire 8 # w_CAT [7:0] $end
$var reg 1 $ r_CLOCK $end
$var reg 8 % r_SHIFT_REG [7:0] $end
$var reg 4 & r_SIGNED [3:0] $end
$var reg 4 ' r_UNSIGNED [3:0] $end
$var reg 4 ( r_VAL_1 [3:0] $end
$var reg 4 ) r_VAL_2 [3:0] $end
$upscope $end
$enddefinitions $end
$comment Show the parameter values. $end
$dumpall
$end
#0
$dumpvars
b1100 )
b111 (
b10 '
b1110 &
b1 %
0$
b1111100 #
b11100010 "
b111110011100010 !
$end
#1
b10 %
1$
#2
0$
#3
b100 %
1$
#4
0$
#5
b1000 %
1$
#6
0$
#7
b10000 %
1$
#8
0$
#9
b100000 %
1$
#10
0$
#11
b1000000 %
1$
#12
0$
#13
b10000000 %
1$
#14
0$
#15
b1 %
1$
#16
0$
#17
b10 %
1$
#18
0$
#19
b100 %
1$
#20
0$
#21
b1000 %
1$
#22
0$
#23
b10000 %
1$
#24
0$
#25
b100000 %
1$
#26
0$
#27
b1000000 %
1$
#28
0$
#29
b10000000 %
1$
#30
0$
#31
b1 %
1$
#32
0$
#33
b10 %
1$
#34
0$
#35
b100 %
1$
#36
0$
#37
b1000 %
1$
#38
0$
#39
b10000 %
1$
#40
0$
#41
b100000 %
1$
#42
0$
#43
b1000000 %
1$
#44
0$
#45
b10000000 %
1$
#46
0$
#47
b1 %
1$
#48
0$
#49
b10 %
1$
#50
0$
#51
b100 %
1$
#52
0$
#53
b1000 %
1$
#54
0$
#55
b10000 %
1$
#56
0$
#57
b100000 %
1$
#58
0$
#59
b1000000 %
1$
#60
0$
#61
b10000000 %
1$
#62
0$
#63
b1 %
1$
#64
0$
#65
b10 %
1$
