shift_operator2.v
module shift_operator2(
  input clock,
  input Input,
  output reg [3:0] Input_Delay
);
  initial begin
  Input_Delay = 4'b0000;
  end

  always @(posedge clock)
    begin
      
      Input_Delay <= Input_Delay << 1;
      Input_Delay[0]<= Input;
    end
  
endmodule

shift_operator2_tb.v
`include "shift_operator2.v"

module tb_shift_operator2;

  reg clock;
  reg Input;
  wire [3:0] Input_Delay;

  shift_operator2 uut (
    .clock(clock),
    .Input(Input),
    .Input_Delay(Input_Delay)
  );

  initial begin
    $dumpfile("shift_operator2.vcd");
    $dumpvars(0, tb_shift_operator2);

    clock = 0;
    Input = 0;
    

    #10 Input = 1;
    #10 Input = 0;
    #10 Input = 1;
    #10 Input = 1;
    #10 Input = 0;

    #40 $finish;
  end

  always #5 clock = ~clock;

endmodule

shift_operator2.vcd
$date
	Thu Mar 26 18:44:43 2026
$end
$version
	Icarus Verilog
$end
$timescale
	1s
$end
$scope module tb_shift_operator2 $end
$var wire 4 ! Input_Delay [3:0] $end
$var reg 1 " Input $end
$var reg 1 # clock $end
$scope module uut $end
$var wire 1 " Input $end
$var wire 1 # clock $end
$var reg 4 $ Input_Delay [3:0] $end
$upscope $end
$upscope $end
$enddefinitions $end
$comment Show the parameter values. $end
$dumpall
$end
#0
$dumpvars
b0 $
0#
0"
b0 !
$end
#5
1#
#10
0#
1"
#15
b1 !
b1 $
1#
#20
0#
0"
#25
b10 !
b10 $
1#
#30
0#
1"
#35
b101 !
b101 $
1#
#40
0#
#45
b1011 !
b1011 $
1#
#50
0#
0"
#55
b110 !
b110 $
1#
#60
0#
#65
b1100 !
b1100 $
1#
#70
0#
#75
b1000 !
b1000 $
1#
#80
0#
#85
b0 !
b0 $
1#
